optikit/Beam.py
optikit/Gaussian.py
optikit/HermiteGauss.py
optikit/InceGauss.py
optikit/LaguerreGauss.py
optikit/__init__.py
optikit/optics.py
OptiKit-0.1.1a11.dist-info/LICENSE
OptiKit-0.1.1a11.dist-info/METADATA
OptiKit-0.1.1a11.dist-info/WHEEL
OptiKit-0.1.1a11.dist-info/top_level.txt
OptiKit-0.1.1a11.dist-info/RECORD
