Metadata-Version: 2.1
Name: OptiKit
Version: 0.1.1a11
Summary: A basic optics module
Home-page: https://github.com/ARMANDOMTZ05/OptiKit
Author: Armando Martinez
Author-email: ar.martinez.hdz@hotmail.com
License: MIT License
Keywords: numpy,optics,holography,slm,python3,wavefront shaping
Classifier: Development Status :: 4 - Beta
Classifier: Intended Audience :: Science/Research
Classifier: License :: OSI Approved :: MIT License
Classifier: Programming Language :: Python :: 3.10
Requires-Python: >=3.10
License-File: LICENSE
Requires-Dist: matplotlib
Requires-Dist: numpy
Requires-Dist: scipy
Requires-Dist: pillow
